namekox_elasticsearch/__init__.py
namekox_elasticsearch/constants.py
namekox_elasticsearch/cli/__init__.py
namekox_elasticsearch/cli/subctx/__init__.py
namekox_elasticsearch/cli/subctx/elasticsearch.py
namekox_elasticsearch/core/__init__.py
namekox_elasticsearch/core/proxy.py
namekox_elasticsearch/core/dependencies/__init__.py
namekox_elasticsearch-7.0.2.dist-info/METADATA
namekox_elasticsearch-7.0.2.dist-info/WHEEL
namekox_elasticsearch-7.0.2.dist-info/top_level.txt
namekox_elasticsearch-7.0.2.dist-info/zip-safe
namekox_elasticsearch-7.0.2.dist-info/RECORD
