Metadata-Version: 2.1
Name: namekox-elasticsearch
Version: 7.0.2
Summary: namekox elasticsearch
Home-page: https://forcemain.github.io/
Author: forcemain
License: Apache License, Version 2.0
Platform: UNKNOWN
Classifier: Programming Language :: Python
Classifier: Operating System :: MacOS :: MacOS X
Classifier: Operating System :: POSIX
Classifier: Programming Language :: Python :: 2
Classifier: Programming Language :: Python :: 2.7
Classifier: Programming Language :: Python :: 3
Classifier: Programming Language :: Python :: 3.5
Classifier: Programming Language :: Python :: 3.6
Classifier: Topic :: Internet
Classifier: Topic :: Software Development :: Libraries :: Python Modules
Classifier: Intended Audience :: Developers
Requires-Dist: namekox-core
Requires-Dist: elasticsearch-dsl (<8.0.0,>=7.0.0)
